[
  {
    "title": "AIが提案する最適なヘアスタイルを美容師がサロンで再現するキャンペーン開催中！",
    "link": "https://straightpress.jp/20240824/1193740",
    "date": "2024-08-24T09:28:43.000Z"
  },
  {
    "title": "Pixel Screenshots: AI-powered screenshot memory + organization",
    "link": "https://store.google.com/intl/en/ideas/articles/pixel-screenshots/",
    "date": "2024-08-24T07:58:59.000Z"
  },
  {
    "title": "Google、スクショの内容を検索するAI機能「Pixel Screenshots」を米国で提供へ",
    "link": "https://www.itmedia.co.jp/mobile/articles/2408/15/news100.html",
    "date": "2024-08-24T07:58:34.000Z"
  },
  {
    "title": "テックリードのポジションを設ける際に考えたこと - Sansan Tech Blog",
    "link": "https://buildersbox.corp-sansan.com/entry/2024/08/23/110000",
    "date": "2024-08-24T06:27:27.000Z"
  },
  {
    "title": "GitHub - opendatalab/MinerU: A one-stop, open-source, high-quality data extraction tool, supports PDF/webpage/e-book extraction.一站式开源高质量数据提取工具，支持PDF/网页/多格式电子书提取。",
    "link": "https://github.com/opendatalab/MinerU",
    "date": "2024-08-24T06:18:18.000Z"
  },
  {
    "title": "「子どもは二人まで」国やメディアが「少子化を推進していた」という歴史的事実（荒川和久） - エキスパート - Yahoo!ニュース",
    "link": "https://news.yahoo.co.jp/expert/articles/d076151b3fd2ffcaff2089edea3f71e1def1a3bd",
    "date": "2024-08-24T06:18:01.000Z"
  },
  {
    "title": "https://www.uber.com/en-AU/blog/shifting-e2e-testing-left/",
    "link": "https://www.uber.com/en-AU/blog/shifting-e2e-testing-left/",
    "date": "2024-08-24T06:17:53.000Z"
  },
  {
    "title": "Ruby Parser開発日誌 (19) - 最高の構文木の設計 2024年版 - かねこにっき",
    "link": "https://yui-knk.hatenablog.com/entry/2024/08/23/113543",
    "date": "2024-08-24T06:07:15.000Z"
  },
  {
    "title": "GitHub - duckdb/pg_duckdb: DuckDB-powered Postgres for high performance apps & analytics.",
    "link": "https://github.com/duckdb/pg_duckdb",
    "date": "2024-08-24T06:06:56.000Z"
  },
  {
    "title": "コサイン類似度とは？　新しい検索体験を支えるベクトルDBの基本技術を押さえる",
    "link": "https://xtech.nikkei.com/atcl/nxt/column/18/02909/081600003/",
    "date": "2024-08-23T23:54:33.000Z"
  },
  {
    "title": "グーグルAI、1000ページのPDFを読んで質問に答えられるように　白書レベルなら余裕",
    "link": "https://ascii.jp/elem/000/004/216/4216929/",
    "date": "2024-08-23T23:51:45.000Z"
  },
  {
    "title": "「多様体」とはどんなもの？　現代数学と現代物理、必須の概念の定義とイメージをつかむ（小笠 英志）",
    "link": "https://gendai.media/articles/-/88722",
    "date": "2024-08-23T23:51:37.000Z"
  },
  {
    "title": "「塊魂」ボーカル楽曲は“禁じ手”戦略だった。制作の秘密が20年を経て明かされる【CEDEC2024】 「作家×歌い手×ジャンル」で揃えた高クオリティ楽曲たち",
    "link": "https://game.watch.impress.co.jp/docs/kikaku/1617680.html",
    "date": "2024-08-23T23:32:50.000Z"
  },
  {
    "title": "安楽死カプセル、年内にも初の実用へ スイス",
    "link": "https://www.afpbb.com/articles/-/3530167",
    "date": "2024-08-23T23:32:46.000Z"
  },
  {
    "title": "睡眠時無呼吸症候群を早期発見したい　「Sleep Doc」を試した【小寺信良のくらしDX】",
    "link": "https://www.watch.impress.co.jp/docs/series/kodera/1617886.html",
    "date": "2024-08-23T23:32:39.000Z"
  },
  {
    "title": "集合をハッシュする (Zobrist hashing)",
    "link": "https://trap.jp/post/1594/",
    "date": "2024-08-23T23:32:31.000Z"
  },
  {
    "title": "新たなWebブラウザ「Verso」など: Cybozu Frontend Weekly (2024-08-20号)",
    "link": "https://zenn.dev/cybozu_frontend/articles/frontend_weekly_20240820",
    "date": "2024-08-23T23:31:34.000Z"
  }
]