[
  {
    "title": "幻聴・幻覚にナイアシンが効く！",
    "link": "http://arekorebibouroku.seesaa.net/article/272899864.html",
    "date": "2014-04-05T14:19:38.000Z"
  },
  {
    "title": "Code for Japanと福島県浪江町が提携---民間技術者を派遣し、ITを活用した地域課題解決を目指す!（佐藤 慶一） @gendai_biz",
    "link": "https://gendai.media/articles/-/38871",
    "date": "2014-04-05T07:08:39.000Z"
  },
  {
    "title": "TechCrunch | Startup and Technology News",
    "link": "https://jp.techcrunch.com/2014/04/05/20140404sitedrop-turns-a-dropbox-folder-into-a-visual-workspace-where-you-can-collaborate-with-others/",
    "date": "2014-04-05T07:07:49.000Z"
  },
  {
    "title": "慢性疲労症候群と脳内炎症の関連を解明 | 理化学研究所",
    "link": "https://www.riken.jp/press/2014/20140404_1/",
    "date": "2014-04-05T06:33:24.000Z"
  },
  {
    "title": "ストーカー:加害者診察１００人超の精神科医に聞く - 毎日新聞",
    "link": "http://mainichi.jp/select/news/20140405k0000e040204000c.html",
    "date": "2014-04-05T06:03:47.000Z"
  },
  {
    "title": "Neo4j GraphGists - graphgists",
    "link": "https://neo4j.com/graphgists/",
    "date": "2014-04-05T05:48:24.000Z"
  },
  {
    "title": "WIXOSS - Wikipedia",
    "link": "https://ja.wikipedia.org/wiki/WIXOSS",
    "date": "2014-04-05T05:47:39.000Z"
  },
  {
    "title": "TechCrunch | Startup and Technology News",
    "link": "https://jp.techcrunch.com/2014/04/01/20140331htc-one-m8-review-the-new-best-android-smartphone/",
    "date": "2014-04-05T05:37:04.000Z"
  },
  {
    "title": "オレとオマエのビットコイン WebLOG弁護士中村真",
    "link": "http://nakamuramakoto.blog112.fc2.com/blog-entry-220.html",
    "date": "2014-04-05T05:36:53.000Z"
  },
  {
    "title": "「苦情」と「クレーム」は違う 誠意を持って話を聞く - ワークスタイル - nikkei BPnet",
    "link": "http://www.nikkeibp.co.jp/style/biz/cover/claim/070911_1st/index2.html",
    "date": "2014-04-05T05:36:49.000Z"
  },
  {
    "title": "不発弾切断し爆発　９人死亡、２０人けが　バンコク | newsclip (ニュース、社会のニュース)",
    "link": "http://www.newsclip.be/article/2014/04/02/21357.html",
    "date": "2014-04-05T05:29:50.000Z"
  },
  {
    "title": "STAP問題を時系列から眺める | kazekiriの日記 | スラド",
    "link": "https://srad.jp/~kazekiri/journal/579627/",
    "date": "2014-04-05T05:29:48.000Z"
  },
  {
    "title": "Amazon.co.jp: 愛着障害 (光文社新書): 岡田尊司: 本",
    "link": "https://www.amazon.co.jp/gp/product/4334036430",
    "date": "2014-04-05T05:29:44.000Z"
  },
  {
    "title": "STAP細胞と研究広報",
    "link": "http://parsonii.blogspot.com/2014/03/stap.html",
    "date": "2014-04-05T05:29:28.000Z"
  },
  {
    "title": "客の顔情報「万引き対策」１１５店が無断共有：ＩＴ＆メディア：読売新聞（YOMIURI ONLINE）",
    "link": "http://www.yomiuri.co.jp/it/20140405-OYT1T50045.html",
    "date": "2014-04-05T04:55:50.000Z"
  },
  {
    "title": "音声認識技術の進化が世界を変える - Nuanceの挑戦",
    "link": "https://news.mynavi.jp/techplus/article/20140404-nuance/",
    "date": "2014-04-05T04:47:19.000Z"
  },
  {
    "title": "ScaleOut | Supership",
    "link": "https://supership.jp/",
    "date": "2014-04-05T04:12:26.000Z"
  },
  {
    "title": "Engadget | Technology News & Reviews",
    "link": "https://japanese.engadget.com/jp-2014-04-04-amazon-dash.html",
    "date": "2014-04-05T04:11:51.000Z"
  },
  {
    "title": "sola : AOSP な Android を作成する手順とソースコードを公開しました",
    "link": "http://blog.sola-dolphin-1.net/archives/4654091.html",
    "date": "2014-04-05T04:11:02.000Z"
  },
  {
    "title": "Amazon Tests Dash Barcode Scanner For Ordering AmazonFresh Groceries | TechCrunch",
    "link": "https://techcrunch.com/2014/04/04/amazon-dash/",
    "date": "2014-04-05T04:10:57.000Z"
  },
  {
    "title": "【実際に作ってみよう！】初心者が1ヶ月でiOS・Android対応のクソゲームアプリを作るための手順 - あのねノート。",
    "link": "http://ottati.hatenablog.com/entry/2014/04/05/105100",
    "date": "2014-04-05T04:07:03.000Z"
  },
  {
    "title": "Windows8.1に統合されたSkyDriveに間違ってもエロ絵を入れてはいけない - 仮想と現実",
    "link": "https://juangotoh.hatenablog.com/entry/2014/04/03/185454",
    "date": "2014-04-05T04:06:41.000Z"
  },
  {
    "title": "大学教員が求める基礎力がつく『数学は言葉』",
    "link": "https://www.anlyznews.com/2014/04/blog-post_5.html",
    "date": "2014-04-05T01:19:23.000Z"
  },
  {
    "title": "小保方氏「入院してもいいですか？」会見キャンセルも （スポーツ報知） - Yahoo!ニュース",
    "link": "http://headlines.yahoo.co.jp/hl?a=20140405-00000021-sph-soci",
    "date": "2014-04-05T01:18:58.000Z"
  },
  {
    "title": "村上春樹は「長編小説」の拡充のためにこそ翻訳や短編の仕事をしているのだけど、僕の「長編小説」はなんなのだろうか - 太陽がまぶしかったから",
    "link": "https://www.du-soleil.com/entry/2014/04/05/090438",
    "date": "2014-04-05T01:09:19.000Z"
  },
  {
    "title": "FXで有り金全部溶かす人の財布 [あいまいみー] | キャラクターグッズ＆アパレル製作販売のコスパ｜COSPA | COSPA,inc.",
    "link": "https://cospa.co.jp/detail/id/00000056632",
    "date": "2014-04-05T01:03:20.000Z"
  },
  {
    "title": "2ちゃんトラブル発表前に社長が株大量売却　インサイダー取引の疑い指摘に会社側は全面否定",
    "link": "http://www.j-cast.com/2014/04/04201309.html?p=all",
    "date": "2014-04-05T00:38:40.000Z"
  },
  {
    "title": "「圏論」は関数プログラミングの「モナド」に役立つ。入門PDF等のリンク集 - 勉強メモ （大学の講義動画や，資格試験の対策）",
    "link": "https://study-guide.hatenablog.jp/entry/20140403/p1",
    "date": "2014-04-05T00:26:35.000Z"
  },
  {
    "title": "TechCrunch | Startup and Technology News",
    "link": "https://jp.techcrunch.com/2014/04/04/20140404finally-someone-is-disrupting-the-towel/",
    "date": "2014-04-05T00:25:36.000Z"
  },
  {
    "title": "AmazonFresh",
    "link": "https://www.amazon.com/fmc/storefront?almBrandId=QW1hem9uIEZyZXNo",
    "date": "2014-04-05T00:18:06.000Z"
  },
  {
    "title": "[字幕動画]Amazonの新サービス「Amazon Dash」は日用品をバーコードスキャナや音声で注文すれば家まで配達してくれる",
    "link": "https://dailynewsagency.com/2014/04/05/amazon-dash-vmw/",
    "date": "2014-04-05T00:18:02.000Z"
  },
  {
    "title": "研究不正再発防止改革推進本部の設置について | 理化学研究所",
    "link": "https://www.riken.jp/pr/news/2014/20140404_1/",
    "date": "2014-04-05T00:13:09.000Z"
  },
  {
    "title": "隣人があまりにも馬鹿騒ぎしていて頭にきたので : ゴールデンタイムズ",
    "link": "http://blog.livedoor.jp/goldennews/archives/51840333.html",
    "date": "2014-04-05T00:12:34.000Z"
  },
  {
    "title": "大人になってから読む120％少女漫画の破壊力――「ディアティア」かずまこを - インターネットもぐもぐ",
    "link": "https://mogmog.hateblo.jp/entry/2014/04/04/002057",
    "date": "2014-04-05T00:10:57.000Z"
  },
  {
    "title": "目黒署管内刃物使用屋内強盗事件　：警視庁",
    "link": "http://www.keishicho.metro.tokyo.jp/jiken/jikenbo/meguro/meguro.htm",
    "date": "2014-04-05T00:10:48.000Z"
  },
  {
    "title": "Grid 日本語版",
    "link": "http://maepon.github.io/grid/",
    "date": "2014-04-05T00:10:38.000Z"
  },
  {
    "title": "慢性副鼻腔炎に効くツボ ～あなたは交感神経タイプ？副交感神経タイプ？～",
    "link": "http://mindedbody.blog108.fc2.com/blog-entry-226.html",
    "date": "2014-04-04T16:22:45.000Z"
  },
  {
    "title": "サービス終了のお知らせ",
    "link": "https://thanks.yahoo.co.jp/Beautycare-Venus/6468/morning_attack.html",
    "date": "2014-04-04T16:19:53.000Z"
  },
  {
    "title": "起床時に、花粉症状が辛くなる「朝の発作」　花粉症の\"モーニングアタック\"調査 | コンタック（風邪薬）",
    "link": "https://contac.jp/soken/release/news_47.html",
    "date": "2014-04-04T16:19:29.000Z"
  },
  {
    "title": "鼻炎 症状 朝",
    "link": "http://nose-inflammation.net/category1/entry1.html",
    "date": "2014-04-04T16:19:16.000Z"
  },
  {
    "title": "花粉症　夜悪化の仕組み解明",
    "link": "http://www.yomidr.yomiuri.co.jp/page.jsp?id=85389",
    "date": "2014-04-04T16:17:54.000Z"
  },
  {
    "title": "税込3万円の10.1型モバイル液晶が発売、10点タッチ対応",
    "link": "https://akiba-pc.watch.impress.co.jp/docs/news/news/642799.html",
    "date": "2014-04-04T16:04:23.000Z"
  },
  {
    "title": "Code for Japanは、技術者を派遣する「フェローシッププログラム」をスタート：第一弾として福島県浪江町への派遣プログラムを開始いたします",
    "link": "http://blog.code4japan.org/post/81638384567/release-namie",
    "date": "2014-04-04T16:04:19.000Z"
  },
  {
    "title": "TechCrunch • Startup and Technology News",
    "link": "https://jp.techcrunch.com/2014/04/04/20140403intel-releases-99-minnowboard-max-an-open-source-single-board-computer/",
    "date": "2014-04-04T16:00:37.000Z"
  },
  {
    "title": "Xamarin入門 – 特徴とインストール、サンプルアプリケーションについて | DevelopersIO",
    "link": "https://dev.classmethod.jp/articles/xamarin-start/",
    "date": "2014-04-04T16:00:10.000Z"
  },
  {
    "title": "AWS Elastic Beanstalkを使って10分でSinatraアプリを動かす | DevelopersIO",
    "link": "https://dev.classmethod.jp/articles/eb-sinatra-in-10minutes/",
    "date": "2014-04-04T16:00:08.000Z"
  },
  {
    "title": "復刊版「ゼノギアス公式設定資料集」の生産金額は、1億円を突破していた ─ 復刊ドットコムの社長が明かす | インサイド",
    "link": "https://www.inside-games.jp/article/2014/04/04/75749.html",
    "date": "2014-04-04T15:57:51.000Z"
  },
  {
    "title": "インテル、99ドルのAndroid／Linuxボード「Minnowboard Max」発売へ",
    "link": "https://ascii.jp/elem/000/000/881/881595/",
    "date": "2014-04-04T15:56:50.000Z"
  },
  {
    "title": "Grafana: The open observability platform | Grafana Labs",
    "link": "https://grafana.com/",
    "date": "2014-04-04T15:56:48.000Z"
  },
  {
    "title": "Blog",
    "link": "https://www.codefellows.org/blog",
    "date": "2014-04-04T15:56:00.000Z"
  },
  {
    "title": "タッチなモバイル液晶「On-Lap」が小型化、その軽快さを活用してみた 実はデスクトップPCでも便利、もちろんノートやタブレットでも text by 日沼 諭史",
    "link": "https://akiba-pc.watch.impress.co.jp/docs/sp/641740.html",
    "date": "2014-04-04T15:54:47.000Z"
  },
  {
    "title": "日本語評価極性辞書 - Open Resources/Japanese Sentiment Polarity Dictionary - 東北大学 乾・岡﨑研究室",
    "link": "http://www.cl.ecei.tohoku.ac.jp/index.php?Open%20Resources%2FJapanese%20Sentiment%20Polarity%20Dictionary",
    "date": "2014-04-04T15:54:08.000Z"
  },
  {
    "title": "全脳アーキテクチャの見取り図",
    "link": "https://staff.aist.go.jp/y-ichisugi/brain-archi/wba-sketch.html",
    "date": "2014-04-04T15:41:11.000Z"
  },
  {
    "title": "ワタミ渡邉美樹氏の記事について謝罪と訂正 : くまニュース",
    "link": "http://blog.livedoor.jp/qmanews/archives/52093009.html",
    "date": "2014-04-04T15:38:25.000Z"
  },
  {
    "title": "ウェアラブルが自作できるように！小型モジュールが30ドルで入手可能 | Techable(テッカブル)",
    "link": "https://techable.jp/archives/12895",
    "date": "2014-04-04T15:02:34.000Z"
  },
  {
    "title": "ごりゅご.com",
    "link": "https://goryugo.com/20140404/anker_40w_usb_charger-2/",
    "date": "2014-04-04T15:01:56.000Z"
  },
  {
    "title": "SamsungのGalaxyバックドア問題の顛末(山本一郎) - 個人 - Yahoo!ニュース",
    "link": "https://news.yahoo.co.jp/byline/yamamotoichiro/20140404-00034238/",
    "date": "2014-04-04T15:01:46.000Z"
  },
  {
    "title": "米Microsoft、JavaScript向けのアプリケーションフレームワーク「WinJS」をオープンソース化 | OSDN Magazine",
    "link": "https://mag.osdn.jp/14/04/04/164500",
    "date": "2014-04-04T15:01:24.000Z"
  },
  {
    "title": "全天球ボール型カメラ「Panono」の撮影イベントが開催　滋賀県の高校ブラスバンド部が日本初の被写体に",
    "link": "https://dc.watch.impress.co.jp/docs/news/642877.html",
    "date": "2014-04-04T15:01:09.000Z"
  }
]