[
  {
    "title": "時論公論　「袴田事件\"国家機関が無実の人を陥れた\"」 | 時論公論 | 解説委員室:NHK",
    "link": "http://www.nhk.or.jp/kaisetsu-blog/100/184128.html",
    "date": "2014-03-29T13:18:28.000Z"
  },
  {
    "title": "「そんなん言うなら辞めます」と言えない社会 - デマこい！",
    "link": "https://rootport.hateblo.jp/entry/20140328/1396017329",
    "date": "2014-03-29T13:10:14.000Z"
  },
  {
    "title": "aBeacon ~iBeacon を Android で受信する~ | ギャップロ",
    "link": "https://gaprot.jp/2014/03/27/abeacon/",
    "date": "2014-03-29T13:08:04.000Z"
  },
  {
    "title": "THE PAGE（ザ・ページ）　|　気になるニュースをわかりやすく",
    "link": "http://thepage.jp/detail/20140329-00000008-wordleaf",
    "date": "2014-03-29T13:07:40.000Z"
  },
  {
    "title": "THE PAGE（ザ・ページ）　|　気になるニュースをわかりやすく",
    "link": "http://thepage.jp/detail/20140328-00000006-wordleaf",
    "date": "2014-03-29T13:07:28.000Z"
  },
  {
    "title": "Cプログラミング診断室 - 藤原博文",
    "link": "http://www.pro.or.jp/~fuji/mybooks/cdiag/index.html",
    "date": "2014-03-29T12:23:21.000Z"
  },
  {
    "title": "報道発表資料：２０５０年を視野に入れた国土づくりに向けて　～新たな「国土のグランドデザイン」（骨子）をとりまとめました～ - 国土交通省",
    "link": "https://www.mlit.go.jp/report/press/kokudoseisaku03_hh_000067.html",
    "date": "2014-03-29T10:52:53.000Z"
  },
  {
    "title": "なぜ html の form は PUT / DELETE をサポートしないのか？ - Block Rockin’ Codes",
    "link": "https://jxck.hatenablog.com/entry/why-form-dosent-support-put-delete",
    "date": "2014-03-29T10:16:46.000Z"
  },
  {
    "title": "イアン・ハッキング『偶然を飼いならす： 統計学と第二次科学革命』 | Theoretical Sociology",
    "link": "http://sociology.jugem.jp/?eid=760",
    "date": "2014-03-29T09:18:04.000Z"
  },
  {
    "title": "オレオレ詐欺、だまされたふり７時間　容疑者逮捕に貢献：朝日新聞デジタル",
    "link": "http://www.asahi.com/articles/ASG3Y30WFG3YUTIL007.html",
    "date": "2014-03-29T07:44:00.000Z"
  },
  {
    "title": "フォント変えれば数百万ドルの節約に、米14歳が政府に提言",
    "link": "https://www.cnn.co.jp/usa/35045853.html",
    "date": "2014-03-29T07:43:49.000Z"
  },
  {
    "title": "台湾:学生ら数百人が立法院占拠　中台協定に反対訴え - 毎日新聞",
    "link": "http://mainichi.jp/select/news/20140320k0000m030072000c.html",
    "date": "2014-03-29T06:43:35.000Z"
  },
  {
    "title": "台湾:「民主主義救う行動だ」立法院占拠の学生指導者 - 毎日新聞",
    "link": "http://mainichi.jp/select/news/20140329k0000m030143000c.html",
    "date": "2014-03-29T06:43:16.000Z"
  },
  {
    "title": "Amazon.co.jp: デザイン仕事に必ず役立つ 図解力アップドリル: 原田泰: 本",
    "link": "https://www.amazon.co.jp/gp/product/4862670903",
    "date": "2014-03-29T06:40:30.000Z"
  },
  {
    "title": "政治献金 - Wikipedia",
    "link": "https://ja.wikipedia.org/wiki/%E6%94%BF%E6%B2%BB%E7%8C%AE%E9%87%91",
    "date": "2014-03-29T00:29:40.000Z"
  },
  {
    "title": "時事ドットコム：８億円は選挙資金＝証拠メール存在、渡辺氏に辞職促す−ＤＨＣ会長",
    "link": "http://www.jiji.com/jc/zc?k=201403/2014032800627&g=pol",
    "date": "2014-03-29T00:20:37.000Z"
  },
  {
    "title": "「刑事司法の理念からは耐え難い不正義」――袴田事件で再審開始＆釈放を命じた決定を読む（江川紹子） - エキスパート - Yahoo!ニュース",
    "link": "https://news.yahoo.co.jp/expert/articles/2001dacb718877cc2de877e881aaf1e0e746660f",
    "date": "2014-03-29T00:20:02.000Z"
  },
  {
    "title": "リクナビに象徴されるネット就活に潜む罠、「誰でも平等に入社のチャンスがある」という幻想が悲劇を生んでないか？ - 竹内研究室の日記",
    "link": "http://d.hatena.ne.jp/Takeuchi-Lab/20140328/1396007747",
    "date": "2014-03-29T00:12:18.000Z"
  },
  {
    "title": "社員数名の開発会社が20人採用したあと黒字をキープするためにやったこと｜TechRacho by BPS株式会社",
    "link": "https://techracho.bpsinc.jp/piichan1031/2014_03_28/16073",
    "date": "2014-03-29T00:09:09.000Z"
  },
  {
    "title": "Fonts.com",
    "link": "https://www.fonts.com/ja/web-fonts/google",
    "date": "2014-03-28T23:39:46.000Z"
  },
  {
    "title": "Windowsで最高のターミナルを構築する方法 - 純粋関数空間",
    "link": "http://tanakh.jp/posts/2011-11-15-windows-terminal.html",
    "date": "2014-03-28T23:33:45.000Z"
  },
  {
    "title": "Google Code Archive - Long-term storage for Google Code Project Hosting.",
    "link": "https://code.google.com/archive/p/mintty/wikis/Keycodes.wiki",
    "date": "2014-03-28T23:31:04.000Z"
  },
  {
    "title": "Google Code Archive - Long-term storage for Google Code Project Hosting.",
    "link": "https://code.google.com/archive/p/mintty/wikis/Keycodes.wiki",
    "date": "2014-03-28T23:30:43.000Z"
  },
  {
    "title": "47NEWS（よんななニュース）",
    "link": "http://www.47news.jp/CN/201403/CN2014032801002445.html",
    "date": "2014-03-28T23:27:06.000Z"
  },
  {
    "title": "見えたぞ雨の立体構造、衛星が初画像を公開",
    "link": "https://news.mynavi.jp/techplus/article/20140328-a042/",
    "date": "2014-03-28T23:22:42.000Z"
  },
  {
    "title": "俺の人生はもう長くない このブログと2ch粘着晒しとの因縁について",
    "link": "https://hatchpotchex.blog.fc2.com/blog-entry-487.html",
    "date": "2014-03-28T23:21:26.000Z"
  },
  {
    "title": "その問題で思った、もう一つのこと: 極東ブログ",
    "link": "http://finalvent.cocolog-nifty.com/fareastblog/2014/03/post-cedd.html",
    "date": "2014-03-28T23:21:12.000Z"
  },
  {
    "title": "サイト閉鎖のお知らせ | iPhonePLUS",
    "link": "http://iphone.ascii.jp/2014/03/26/32432432/",
    "date": "2014-03-28T23:20:20.000Z"
  },
  {
    "title": "今夜は品川で火鍋とiBeacon体験、オーダーはすべてiPhoneでオッケー｜Mac - 週刊アスキー",
    "link": "https://weekly.ascii.jp/elem/000/002/622/2622004/?r=1",
    "date": "2014-03-28T23:20:13.000Z"
  },
  {
    "title": "iBeacon＋実店舗の初仕事がリリースされました（＆独立のご報告） - その後のその後",
    "link": "https://shu223.hatenablog.com/entry/20140326/1395835542",
    "date": "2014-03-28T23:19:29.000Z"
  },
  {
    "title": "横浜赤レンガ倉庫で無料Wi-Fi、ランプサーブのLED可視光通信活用",
    "link": "https://xtech.nikkei.com/it/article/NEWS/20140327/546725/",
    "date": "2014-03-28T23:19:14.000Z"
  },
  {
    "title": "Amazon.co.jp: データベース徹底攻略 (WEB+DB PRESS plus): 松信嘉範 (著), 羽生章洋 (著), ミック (著), 奥野幹也 (著), 松下雅和 (著), 桑野章弘 (著), 青木峰郎 (著), ひろせまさあき (著), 小林篤 (著), 島田慶樹 (著), WEB+DB PRESS編集部 (編集): 本",
    "link": "https://www.amazon.co.jp/gp/product/4774163651",
    "date": "2014-03-28T23:18:20.000Z"
  },
  {
    "title": "ムック「データベース徹底攻略」 - MySQL/Redis/MongoDB/Redshift",
    "link": "http://opendatabaselife.blogspot.com/2014/03/mysqlredismongodbredshift.html",
    "date": "2014-03-28T23:18:03.000Z"
  },
  {
    "title": "【すき家】ゼンショー小川社長インタビュー(1/2) - 日経ビジネスオンライン",
    "link": "http://business.nikkeibp.co.jp/article/manage/20100917/216295/",
    "date": "2014-03-28T23:16:16.000Z"
  },
  {
    "title": "【すき家】 ゼンショー小川社長インタビュー - 日経ビジネスオンライン",
    "link": "http://business.nikkeibp.co.jp/article/manage/20100924/216369/",
    "date": "2014-03-28T23:16:03.000Z"
  },
  {
    "title": "USB充電器の設計技法",
    "link": "https://edn.itmedia.co.jp/edn/articles/0806/01/news013.html",
    "date": "2014-03-28T23:13:42.000Z"
  },
  {
    "title": "HoverBall : Augmented Sports with a Flying Ball",
    "link": "https://lab.rekimoto.org/projects/hoverball/",
    "date": "2014-03-28T23:11:27.000Z"
  },
  {
    "title": "東大がドローンを内蔵したボール「HoverBall」を開発 - DMM 3Dプリント × THE BRIDGE",
    "link": "http://make.thebridge.jp/2014/03/hoverball",
    "date": "2014-03-28T23:11:13.000Z"
  },
  {
    "title": "Bluetooth LEとiBeaconを使った、すれ違い通信",
    "link": "https://www.slideshare.net/slideshow/bluetooth-leibeacon/32626286",
    "date": "2014-03-28T23:08:40.000Z"
  },
  {
    "title": "UP2 by Jawbone | A Smarter Activity Tracker For A Fitter You",
    "link": "http://jawbone.com/store/buy/up24",
    "date": "2014-03-28T23:07:17.000Z"
  },
  {
    "title": "Engadget | Technology News & Reviews",
    "link": "https://japanese.engadget.com/jp-2014-03-27-jawbone-up24-bluetooth-smart.html",
    "date": "2014-03-28T23:06:05.000Z"
  },
  {
    "title": "TechCrunch | Startup and Technology News",
    "link": "https://jp.techcrunch.com/2014/03/26/20140323sonys-advantage/",
    "date": "2014-03-28T23:00:40.000Z"
  },
  {
    "title": "電車にひかれ6時間　足切断、自ら119番　JR唐津駅：朝日新聞デジタル",
    "link": "http://www.asahi.com/articles/ASG3V34FKG3VTTHB002.html",
    "date": "2014-03-28T22:56:26.000Z"
  },
  {
    "title": "宮崎技術研究所の技術講座「実用ノイズ対策技術」",
    "link": "http://www.miyazaki-gijutsu.com/series2/index.html",
    "date": "2014-03-28T22:52:41.000Z"
  },
  {
    "title": "小さな組織の未来学",
    "link": "http://www.nikkeibp.co.jp/miraigaku/index.html",
    "date": "2014-03-28T22:51:07.000Z"
  },
  {
    "title": "http://shibuya-ar-jikken.jp/",
    "link": "http://shibuya-ar-jikken.jp/",
    "date": "2014-03-28T22:48:08.000Z"
  },
  {
    "title": "地下街やビル内でも歩行者ナビ、渋谷で実験",
    "link": "https://k-tai.watch.impress.co.jp/docs/news/641086.html",
    "date": "2014-03-28T22:47:59.000Z"
  },
  {
    "title": "扬中帐潜装饰工程有限公司",
    "link": "http://www.elelab-net.com/hobbytec/?cat=9",
    "date": "2014-03-28T22:43:08.000Z"
  },
  {
    "title": "Make: Japan | Raspberry Piを首振り式のカメラに",
    "link": "https://makezine.jp/blog/2014/03/pi_pan.html",
    "date": "2014-03-28T22:42:59.000Z"
  },
  {
    "title": "Stanford大学の自然言語処理講座（1-1）NLPの世界へようこそ！ | Synergy Marketing LAB",
    "link": "http://lab.synergy-marketing.co.jp/blog/nlp/nlp_stanford1-1",
    "date": "2014-03-28T22:42:24.000Z"
  },
  {
    "title": "https://alaginrc.nict.go.jp/rasc/",
    "link": "https://alaginrc.nict.go.jp/rasc/",
    "date": "2014-03-28T22:42:12.000Z"
  },
  {
    "title": "チョムスキーの来日講演の動画",
    "link": "http://oyukio.blogspot.com/2014/03/blog-post_27.html",
    "date": "2014-03-28T22:39:56.000Z"
  },
  {
    "title": "ノーム・チョムスキー教授講演会 The Architecture of Language Reconsidered 「言語の構成原理再考」・Capitalist Democracy and the Prospects for Survival 「資本主義的民主制の下で人類は生き残れるか」 – 上智大学OpenCourseWare",
    "link": "https://ocw.cc.sophia.ac.jp/lecture/20140305linstic/",
    "date": "2014-03-28T22:38:09.000Z"
  },
  {
    "title": "Chomsky Syntax Session 2014 Keio Linguistic Colloquium - ニュース・イベント",
    "link": "http://www.icl.keio.ac.jp/news/2014/03/chomsky-syntax-session-2014-keio-linguistic-colloquium.html",
    "date": "2014-03-28T22:38:00.000Z"
  },
  {
    "title": "ビッグデータ技術を用いたグラフ処理",
    "link": "https://www.infoq.com/jp/news/2014/03/graph-bigdata-tapad/",
    "date": "2014-03-28T22:37:23.000Z"
  },
  {
    "title": "“エウリアン”も客引き通りもアウト？　東京・千代田区「客引き禁止」条例について聞いてみた",
    "link": "https://nlab.itmedia.co.jp/nl/articles/1403/20/news129.html",
    "date": "2014-03-28T22:32:56.000Z"
  },
  {
    "title": "「気分の波」を緩和する薬剤の作用メカニズム解明に一歩前進 | 60秒でわかるプレスリリース | 理化学研究所",
    "link": "http://www.riken.jp/pr/press/2014/20140213_1/digest/",
    "date": "2014-03-28T22:31:56.000Z"
  },
  {
    "title": "「気分の波」を緩和する薬剤の作用メカニズム解明に一歩前進 | 理化学研究所",
    "link": "https://www.riken.jp/press/2014/20140213_1/",
    "date": "2014-03-28T22:31:41.000Z"
  },
  {
    "title": "ゼロから始めるDeepLearning_その1_ニューラルネットとは - 分からんこと多すぎ",
    "link": "https://rishida.hatenablog.com/entry/2014/02/25/110643",
    "date": "2014-03-28T22:17:55.000Z"
  },
  {
    "title": "脳で直接コミュニケーションする未来へ、必要なブレイクスルーは何なのか聞いてきた。",
    "link": "https://www.gizmodo.jp/2014/03/brain-machine-interface_ricoh2036.html",
    "date": "2014-03-28T22:17:07.000Z"
  },
  {
    "title": "Tenderlove Making | tenderlovemaking.com",
    "link": "http://tenderlovemaking.com/",
    "date": "2014-03-28T22:13:15.000Z"
  },
  {
    "title": "GeoNode",
    "link": "https://geonode.org/",
    "date": "2014-03-28T22:12:36.000Z"
  },
  {
    "title": "サードパーティJavaScript - それはBooks",
    "link": "http://hamasyou.com/blog/2014/02/23/third-party-javascript/",
    "date": "2014-03-28T22:11:53.000Z"
  },
  {
    "title": "TVアニメ「健全ロボ ダイミダラー」公式サイト",
    "link": "http://penguin-empire.com/",
    "date": "2014-03-28T22:10:54.000Z"
  },
  {
    "title": "GitHub: ストレスをうまく減らしているのがキモなんだと思った - ワザノバ | wazanova",
    "link": "http://wazanova.jp/items/1187",
    "date": "2014-03-28T22:09:59.000Z"
  },
  {
    "title": "アルバイト・パート採用 学生の方のご応募も歓迎 - 株式会社はてな",
    "link": "https://hatena.co.jp/recruit/arbeit",
    "date": "2014-03-28T22:05:37.000Z"
  },
  {
    "title": "「僕にとってゲームは悪」だが……富野由悠季氏、ゲーム開発者を鼓舞",
    "link": "https://www.itmedia.co.jp/news/articles/0909/02/news089.html",
    "date": "2014-03-28T22:02:37.000Z"
  },
  {
    "title": "WebScaleSQL | \"We're Gonna Need A Bigger Database\"",
    "link": "http://webscalesql.org/",
    "date": "2014-03-28T22:01:04.000Z"
  },
  {
    "title": "読み取り権限がなく実行権限だけのファイルが実行できるのはなぜ？ - カーネルのソースを読む - - 猫型の蓄音機は 1 分間に 45 回にゃあと鳴く",
    "link": "https://nekogata.hatenablog.com/entry/2014/03/28/060547",
    "date": "2014-03-28T22:00:56.000Z"
  },
  {
    "title": "社内勉強会を居酒屋でやってみたら - HOW TO GO",
    "link": "https://sugiim.hatenablog.com/entry/2013/03/07/001456",
    "date": "2014-03-28T22:00:21.000Z"
  },
  {
    "title": "悪夢と通常夢と明晰夢（その１　悪夢への対処方法） : 場末Ｐ科病院の精神科医のblog",
    "link": "http://blog.livedoor.jp/beziehungswahn/archives/37300953.html",
    "date": "2014-03-28T21:57:47.000Z"
  },
  {
    "title": "空間除菌グッズは「根拠なし」 - NHK 首都圏 NEWS WEB",
    "link": "http://www3.nhk.or.jp/shutoken-news/20140327/3225861.html",
    "date": "2014-03-28T21:54:10.000Z"
  },
  {
    "title": "JSオジサン＃1 LT「node-webkitとchrome-remote-interfaceでブラウザオートメーション」 - ayapi.github.io",
    "link": "http://ayapi.github.io/posts/jsojisan1/",
    "date": "2014-03-28T21:51:51.000Z"
  },
  {
    "title": "FacebookやGoogle、「WebScaleSQL」をオープンソースで公開",
    "link": "https://www.itmedia.co.jp/news/articles/1403/28/news054.html",
    "date": "2014-03-28T21:51:03.000Z"
  },
  {
    "title": "プレゼン用のスライドショーを実装する、わずか1KBなのに多彩なエフェクトを備えタッチデバイスにも対応したスクリプト -Bespoke.js",
    "link": "https://coliss.com/articles/build-websites/operation/javascript/presentation-micro-framework-bespoke-js.html",
    "date": "2014-03-28T21:49:23.000Z"
  },
  {
    "title": "【個人メモ】bespoke.jsを使ってプレゼン資料を作成する - Qiita",
    "link": "https://qiita.com/futoase/items/4a341f452c4a9c9b1bbb",
    "date": "2014-03-28T21:48:20.000Z"
  },
  {
    "title": "クラウド査読により透明になるアカデミア - クマムシ博士のむしブロ",
    "link": "https://horikawad.hatenadiary.com/entry/2014/03/28/232550",
    "date": "2014-03-28T21:43:42.000Z"
  },
  {
    "title": "フリーフォント「はらませにゃんこ」",
    "link": "http://inatsuka.com/extra/haranyan/",
    "date": "2014-03-28T21:41:11.000Z"
  },
  {
    "title": "エロゲーマーはエロゲのエロシーンでナニを見ているのか？ - strangelet",
    "link": "http://strangelet.hatenablog.jp/entry/http%3A//www_getchu_com/pc/2013_g_ranking/",
    "date": "2014-03-28T21:31:57.000Z"
  },
  {
    "title": "福島第一で作業員生き埋め、死亡…収束作業で初 : 社会 : YOMIURI ONLINE（読売新聞）",
    "link": "http://www.yomiuri.co.jp/national/news/20140328-OYT1T00514.htm",
    "date": "2014-03-28T15:30:15.000Z"
  },
  {
    "title": "横浜市が酒臭い職員を減給処分に　市民から苦情も - 芸能社会 - SANSPO.COM（サンスポ）",
    "link": "http://www.sanspo.com/geino/news/20140328/tro14032812530005-n1.html",
    "date": "2014-03-28T15:29:37.000Z"
  },
  {
    "title": "家にいながらアニメの舞台に！「聖地巡礼マップ」サービス開始",
    "link": "https://kai-you.net/article/4269",
    "date": "2014-03-28T15:26:56.000Z"
  }
]